auth_lib/__init__.py
auth_lib/aiomethods.py
auth_lib/exceptions.py
auth_lib/fastapi.py
auth_lib/methods.py
auth_lib/airflow/__init__.py
auth_lib/airflow/auth_api.py
auth_lib/airflow/auth_ui.py
auth_lib/testing/__init__.py
auth_lib/testing/testutils.py
auth_lib_profcomff-2024.8.4.dist-info/LICENSE
auth_lib_profcomff-2024.8.4.dist-info/METADATA
auth_lib_profcomff-2024.8.4.dist-info/WHEEL
auth_lib_profcomff-2024.8.4.dist-info/entry_points.txt
auth_lib_profcomff-2024.8.4.dist-info/top_level.txt
auth_lib_profcomff-2024.8.4.dist-info/RECORD
