Metadata-Version: 2.1
Name: auth_lib_profcomff
Version: 2024.8.4
Summary: Библиотека функций авторизации для микросервисов Твой ФФ!
Author-email: "profcomff.com" <admin@profcomff.com>, Semyon Grigoriev <grigoriev@profcomff.com>, Roman Dyakov <roman@dyakov.space>
License: BSD 3-Clause License
Project-URL: Homepage, https://app.profcomff.com
Project-URL: Documentation, https://github.com/profcomff/auth-lib/blob/main/README.md
Project-URL: Repository, https://github.com/profcomff/auth-lib
Project-URL: Issues, https://github.com/profcomff/auth-lib/issues
Project-URL: Changelog, https://github.com/profcomff/auth-lib/releases
Classifier: Development Status :: 5 - Production/Stable
Classifier: Programming Language :: Python :: 3
Classifier: Programming Language :: Python :: 3.11
Requires-Python: >=3.10
License-File: LICENSE
Requires-Dist: requests
Provides-Extra: aio
Requires-Dist: aiohttp; extra == "aio"
Provides-Extra: fastapi
Requires-Dist: fastapi; extra == "fastapi"
Requires-Dist: starlette; extra == "fastapi"
Requires-Dist: pydantic; extra == "fastapi"
Requires-Dist: pydantic_settings; extra == "fastapi"
Provides-Extra: airflow
Requires-Dist: flask; extra == "airflow"
Requires-Dist: apache-airflow; extra == "airflow"
Provides-Extra: testing
Requires-Dist: pytest; extra == "testing"
Requires-Dist: pytest-cov; extra == "testing"
Requires-Dist: pytest-mock; extra == "testing"
Requires-Dist: httpx; extra == "testing"
Requires-Dist: requests; extra == "testing"
Provides-Extra: style
Requires-Dist: black; extra == "style"
Requires-Dist: isort; extra == "style"
Requires-Dist: pydocstyle; extra == "style"
Requires-Dist: autoflake; extra == "style"
